[
{ "tourId": 1, "locationId": 1 },
{ "tourId": 2, "locationId": 1 },
{ "tourId": 3, "locationId": 1 },
{ "tourId": 4, "locationId": 1 },
{ "tourId": 5, "locationId": 1 },
{ "tourId": 6, "locationId": 1 },
{ "tourId": 7, "locationId": 1 },
{ "tourId": 8, "locationId": 1 },
{ "tourId": 9, "locationId": 1 },
{ "tourId": 10, "locationId": 1 },
  { "tourId": 11, "locationId": 1 },
  { "tourId": 12, "locationId": 1 },
  { "tourId": 13, "locationId": 1 },
  { "tourId": 14, "locationId": 1 },
  { "tourId": 15, "locationId": 1 },
  { "tourId": 16, "locationId": 1 },
  { "tourId": 17, "locationId": 1 },
  { "tourId": 18, "locationId": 1 },
  { "tourId": 19, "locationId": 1 },
  { "tourId": 20, "locationId": 1 },
  { "tourId": 21, "locationId": 1 },
  { "tourId": 22, "locationId": 1 },
  { "tourId": 23, "locationId": 1 },
  { "tourId": 24, "locationId": 1 },
  { "tourId": 25, "locationId": 1 },
  { "tourId": 26, "locationId": 1 },
  { "tourId": 27, "locationId": 1 },
  { "tourId": 28, "locationId": 1 },
  { "tourId": 29, "locationId": 1 },
  { "tourId": 30, "locationId": 1 },
  { "tourId": 31, "locationId": 1 },
  { "tourId": 32, "locationId": 1 },
  { "tourId": 33, "locationId": 1 },
  { "tourId": 34, "locationId": 1 },
  { "tourId": 35, "locationId": 1 },
  { "tourId": 36, "locationId": 1 },
  { "tourId": 37, "locationId": 1 },
  { "tourId": 38, "locationId": 1 },
  { "tourId": 39, "locationId": 1 },
  { "tourId": 40, "locationId": 1 },
  { "tourId": 41, "locationId": 1 },
  { "tourId": 42, "locationId": 1 },
  { "tourId": 43, "locationId": 1 },
  { "tourId": 44, "locationId": 1 },
  { "tourId": 45, "locationId": 1 },
  { "tourId": 46, "locationId": 1 },
  { "tourId": 47, "locationId": 1 },
  { "tourId": 48, "locationId": 1 },
  { "tourId": 49, "locationId": 1 },
  { "tourId": 50, "locationId": 1 },
  { "tourId": 51, "locationId": 1 },
  { "tourId": 52, "locationId": 1 },
  { "tourId": 53, "locationId": 1 },
  { "tourId": 54, "locationId": 1 },
  { "tourId": 55, "locationId": 1 },
  { "tourId": 56, "locationId": 1 },
  { "tourId": 57, "locationId": 1 },
  { "tourId": 58, "locationId": 1 },
  { "tourId": 59, "locationId": 1 },
  { "tourId": 60, "locationId": 1 },
  { "tourId": 61, "locationId": 1 },
  { "tourId": 62, "locationId": 1 },
  { "tourId": 63, "locationId": 1 },
  { "tourId": 64, "locationId": 1 },
  { "tourId": 65, "locationId": 1 },
  { "tourId": 66, "locationId": 1 },
  { "tourId": 67, "locationId": 1 },
  { "tourId": 68, "locationId": 1 },
  { "tourId": 69, "locationId": 1 },
  { "tourId": 70, "locationId": 1 },
  { "tourId": 71, "locationId": 1 },
  { "tourId": 72, "locationId": 1 },
  { "tourId": 73, "locationId": 1 },
  { "tourId": 74, "locationId": 1 },
  { "tourId": 75, "locationId": 1 },
  { "tourId": 76, "locationId": 1 },
  { "tourId": 77, "locationId": 1 },
  { "tourId": 78, "locationId": 1 },
  { "tourId": 79, "locationId": 1 },
  { "tourId": 80, "locationId": 1 },
  { "tourId": 81, "locationId": 1 },
  { "tourId": 82, "locationId": 1 },
  { "tourId": 83, "locationId": 1 },
  { "tourId": 84, "locationId": 1 },
  { "tourId": 85, "locationId": 1 },
  { "tourId": 86, "locationId": 1 },
  { "tourId": 87, "locationId": 1 },
  { "tourId": 88, "locationId": 1 },
  { "tourId": 89, "locationId": 1 },
  { "tourId": 1001, "locationId": 1 },
  { "tourId": 1002, "locationId": 1 },
  { "tourId": 1003, "locationId": 1 },
  { "tourId": 1004, "locationId": 1 },
  { "tourId": 1005, "locationId": 1 },
  { "tourId": 1006, "locationId": 1 },
  { "tourId": 1007, "locationId": 1 },
  { "tourId": 1008, "locationId": 1 },
  { "tourId": 1009, "locationId": 1 },
  { "tourId": 1010, "locationId": 1 },
  { "tourId": 1011, "locationId": 1 },
  { "tourId": 1012, "locationId": 1 },
  { "tourId": 1013, "locationId": 1 },
  { "tourId": 1014, "locationId": 1 },
  { "tourId": 1015, "locationId": 1 }



  ]